lab_text_processing/__init__.py
lab_text_processing/__version__.py
lab_text_processing/nltk.py
lab_text_processing/pre_processing.py
lab_text_processing/stemmize.py
lab_text_processing/stopwords.py
lab_text_processing-0.2.0.dist-info/METADATA
lab_text_processing-0.2.0.dist-info/RECORD
lab_text_processing-0.2.0.dist-info/WHEEL
lab_text_processing-0.2.0.dist-info/top_level.txt
