Metadata-Version: 2.1
Name: lab-text-processing
Version: 0.2.0
Summary: Functions to text processing
Home-page: https://github.com/labhackercd/lab-text-processing
Author: msfernandes
Author-email: matheus.souza.fernandes@gmail.com
License: MIT
Platform: UNKNOWN
Classifier: License :: OSI Approved :: MIT License
Classifier: Programming Language :: Python
Classifier: Programming Language :: Python :: 3
Classifier: Programming Language :: Python :: 3.6
Requires-Python: >=3
Requires-Dist: nltk
Requires-Dist: fcache
